odoo8_addon_account_payment_order_sequence-8.0.1.0.0-py2.7-nspkg.pth
odoo_addons/account_payment_order_sequence/__openerp__.py
odoo_addons/account_payment_order_sequence/__init__.py
odoo_addons/account_payment_order_sequence/README.rst
odoo_addons/account_payment_order_sequence/models/payment_mode.py
odoo_addons/account_payment_order_sequence/models/payment_order.py
odoo_addons/account_payment_order_sequence/models/__init__.py
odoo_addons/account_payment_order_sequence/views/payment_mode_views.xml
odoo_addons/account_payment_order_sequence/tests/test_payment_order.py
odoo_addons/account_payment_order_sequence/tests/__init__.py
odoo_addons/account_payment_order_sequence/static/description/icon.png
odoo8_addon_account_payment_order_sequence-8.0.1.0.0.dist-info/top_level.txt
odoo8_addon_account_payment_order_sequence-8.0.1.0.0.dist-info/WHEEL
odoo8_addon_account_payment_order_sequence-8.0.1.0.0.dist-info/RECORD
odoo8_addon_account_payment_order_sequence-8.0.1.0.0.dist-info/metadata.json
odoo8_addon_account_payment_order_sequence-8.0.1.0.0.dist-info/DESCRIPTION.rst
odoo8_addon_account_payment_order_sequence-8.0.1.0.0.dist-info/METADATA
odoo8_addon_account_payment_order_sequence-8.0.1.0.0.dist-info/namespace_packages.txt
